readthedocs_cli/__init__.py
readthedocs_cli/__main__.py
readthedocs_cli/api/__init__.py
readthedocs_cli/api/unofficial.py
readthedocs_cli/api/v3.py
readthedocs_cli-5.dist-info/LICENSE
readthedocs_cli-5.dist-info/METADATA
readthedocs_cli-5.dist-info/WHEEL
readthedocs_cli-5.dist-info/entry_points.txt
readthedocs_cli-5.dist-info/top_level.txt
readthedocs_cli-5.dist-info/RECORD
