Metadata-Version: 2.1
Name: readthedocs-cli
Version: 5
Summary: A CLI for the Read The Docs v3 API
Home-page: https://github.com/nextstrain/readthedocs-cli
Author: Thomas Sibley
Author-email: tsibley@fredhutch.org
Project-URL: Bug Tracker, https://github.com/nextstrain/readthedocs-cli
Classifier: Programming Language :: Python :: 3
Classifier: License :: OSI Approved :: MIT License
Classifier: Operating System :: OS Independent
Requires-Python: >=3.6
License-File: LICENSE
Requires-Dist: click>=8
Requires-Dist: requests>=2.30.0
Requires-Dist: rich
Requires-Dist: pyyaml
Requires-Dist: urllib3>=2.0.0
Provides-Extra: maintainers-sync
Requires-Dist: beautifulsoup4; extra == "maintainers-sync"
Requires-Dist: browser-cookie3; extra == "maintainers-sync"
